infi.execute-0.1.8-py2.7-nspkg.pth
infi/execute/__init__.py
infi/execute/__version__.py
infi/execute/exceptions.py
infi/execute/ioloop.py
infi/execute/result.py
infi/execute/runner.py
infi/execute/utils.py
infi/execute/waiting.py
infi.execute-0.1.8.dist-info/DESCRIPTION.rst
infi.execute-0.1.8.dist-info/METADATA
infi.execute-0.1.8.dist-info/RECORD
infi.execute-0.1.8.dist-info/WHEEL
infi.execute-0.1.8.dist-info/entry_points.txt
infi.execute-0.1.8.dist-info/metadata.json
infi.execute-0.1.8.dist-info/namespace_packages.txt
infi.execute-0.1.8.dist-info/top_level.txt
